setup.py
monologue/__init__.py
monologue/core.py
monologue.egg-info/PKG-INFO
monologue.egg-info/SOURCES.txt
monologue.egg-info/dependency_links.txt
monologue.egg-info/namespace_packages.txt
monologue.egg-info/not-zip-safe
monologue.egg-info/requires.txt
monologue.egg-info/top_level.txt