Metadata-Version: 1.0
Name: monologue
Version: 0.0.0beta
Summary: Monologue - processing messages and progress display
Home-page: UNKNOWN
Author: Feth AREZKI
Author-email: feth <at> tuttu.info
License: UNKNOWN
Keywords: logging
Platform: UNKNOWN
